README.md
setup.cfg
setup.py
TOPSIS_ANMOL_101803669/__init__.py
TOPSIS_ANMOL_101803669/topsis1.py
TOPSIS_ANMOL_101803669.egg-info/PKG-INFO
TOPSIS_ANMOL_101803669.egg-info/SOURCES.txt
TOPSIS_ANMOL_101803669.egg-info/dependency_links.txt
TOPSIS_ANMOL_101803669.egg-info/requires.txt
TOPSIS_ANMOL_101803669.egg-info/top_level.txt