Metadata-Version: 2.1
Name: TOPSIS-ANMOL-101803669
Version: 0.2
Summary: THIS PACKAGE IS TO IMPLEMENT TOPSIS
Home-page: UNKNOWN
Author: ANMOL JINDAL
Author-email: ajindal4_be18@thapar.edu
License: MIT
Platform: UNKNOWN
Classifier: Development Status :: 3 - Alpha
Classifier: Intended Audience :: Developers
Classifier: Topic :: Software Development :: Build Tools
Classifier: License :: OSI Approved :: MIT License
Classifier: Programming Language :: Python :: 3
Classifier: Programming Language :: Python :: 3.4
Classifier: Programming Language :: Python :: 3.5
Classifier: Programming Language :: Python :: 3.6
